netbox_announcement/__init__.py
netbox_announcement/admin.py
netbox_announcement/choices.py
netbox_announcement/filters.py
netbox_announcement/forms.py
netbox_announcement/models.py
netbox_announcement/navigation.py
netbox_announcement/tables.py
netbox_announcement/template_content.py
netbox_announcement/urls.py
netbox_announcement/views.py
netbox_announcement/api/serializers.py
netbox_announcement/api/urls.py
netbox_announcement/api/views.py
netbox_announcement/doc/announcement.md
netbox_announcement/templates/netbox_announcement/announcement_detail.html
netbox_announcement/templates/netbox_announcement/announcement_edit.html
netbox_announcement/templates/netbox_announcement/announcement_edit_device.html
netbox_announcement/templates/netbox_announcement/announcement_edit_network.html
netbox_announcement/templates/netbox_announcement/announcement_edit_vm.html
netbox_announcement/templates/netbox_announcement/announcement_list.html
netbox_announcement/templates/netbox_announcement/announcement_update_edit.html
netbox_announcement/templates/netbox_announcement/announcement_update_table.html
netbox_announcement/templates/netbox_announcement/device/announcement_table.html
netbox_announcement/templates/netbox_announcement/device/announcementlist_btn.html
netbox_announcement/templates/netbox_announcement/device/latest_announcements.html
netbox_announcement/templates/netbox_announcement/inc/announcement_edit_header.html
netbox_announcement/templates/netbox_announcement/vm/announcement_table.html
netbox_announcement/templates/netbox_announcement/vm/announcementlist_btn.html
netbox_announcement/templates/netbox_announcement/vm/latest_announcements.html
netbox_announcement-1.1.3.dist-info/METADATA
netbox_announcement-1.1.3.dist-info/WHEEL
netbox_announcement-1.1.3.dist-info/top_level.txt
netbox_announcement-1.1.3.dist-info/RECORD
