Metadata-Version: 2.1
Name: netbox-announcement
Version: 1.1.3
Summary: A NetBox announcement plugin
Home-page: https://github.com/vas-git/netbox-announcement
Author: Vasilatos Vitaliy
License: Apache 2.0
Platform: UNKNOWN
